odoo/addons/l10n_es_aeat/README.rst
odoo/addons/l10n_es_aeat/__init__.py
odoo/addons/l10n_es_aeat/__manifest__.py
odoo/addons/l10n_es_aeat/data/aeat_partner.xml
odoo/addons/l10n_es_aeat/data/aeat_tax_agency_data.xml
odoo/addons/l10n_es_aeat/data/ir_config_parameter.xml
odoo/addons/l10n_es_aeat/i18n/bg.po
odoo/addons/l10n_es_aeat/i18n/ca.po
odoo/addons/l10n_es_aeat/i18n/cs.po
odoo/addons/l10n_es_aeat/i18n/de.po
odoo/addons/l10n_es_aeat/i18n/en.po
odoo/addons/l10n_es_aeat/i18n/es.po
odoo/addons/l10n_es_aeat/i18n/es_CO.po
odoo/addons/l10n_es_aeat/i18n/es_CR.po
odoo/addons/l10n_es_aeat/i18n/eu.po
odoo/addons/l10n_es_aeat/i18n/fr.po
odoo/addons/l10n_es_aeat/i18n/gl.po
odoo/addons/l10n_es_aeat/i18n/hr.po
odoo/addons/l10n_es_aeat/i18n/l10n_es_aeat.pot
odoo/addons/l10n_es_aeat/i18n/nl.po
odoo/addons/l10n_es_aeat/i18n/pl.po
odoo/addons/l10n_es_aeat/i18n/pt.po
odoo/addons/l10n_es_aeat/i18n/pt_BR.po
odoo/addons/l10n_es_aeat/i18n/ru.po
odoo/addons/l10n_es_aeat/i18n/sl.po
odoo/addons/l10n_es_aeat/i18n/sv.po
odoo/addons/l10n_es_aeat/i18n/tr.po
odoo/addons/l10n_es_aeat/i18n/vi.po
odoo/addons/l10n_es_aeat/models/__init__.py
odoo/addons/l10n_es_aeat/models/aeat_certificate.py
odoo/addons/l10n_es_aeat/models/aeat_soap.py
odoo/addons/l10n_es_aeat/models/aeat_tax_agency.py
odoo/addons/l10n_es_aeat/models/l10n_es_aeat_export_config.py
odoo/addons/l10n_es_aeat/models/l10n_es_aeat_export_config_line.py
odoo/addons/l10n_es_aeat/models/l10n_es_aeat_map_tax.py
odoo/addons/l10n_es_aeat/models/l10n_es_aeat_map_tax_line.py
odoo/addons/l10n_es_aeat/models/l10n_es_aeat_report.py
odoo/addons/l10n_es_aeat/models/l10n_es_aeat_report_tax_mapping.py
odoo/addons/l10n_es_aeat/models/l10n_es_aeat_tax_line.py
odoo/addons/l10n_es_aeat/models/res_company.py
odoo/addons/l10n_es_aeat/models/res_partner.py
odoo/addons/l10n_es_aeat/models/res_partner_bank.py
odoo/addons/l10n_es_aeat/models/spanish_states_mapping.py
odoo/addons/l10n_es_aeat/readme/CONFIGURE.rst
odoo/addons/l10n_es_aeat/readme/CONTRIBUTORS.rst
odoo12_addon_l10n_es_aeat-12.0.3.0.0.dist-info/METADATA
odoo12_addon_l10n_es_aeat-12.0.3.0.0.dist-info/WHEEL
odoo12_addon_l10n_es_aeat-12.0.3.0.0.dist-info/top_level.txt
odoo12_addon_l10n_es_aeat-12.0.3.0.0.dist-info/RECORD
